{
  "project_info": {
    "project_number": "230792036216",
    "firebase_url": "https://finalproject3d-ac1ff-default-rtdb.asia-southeast1.firebasedatabase.app",
    "project_id": "finalproject3d-ac1ff",
    "storage_bucket": "finalproject3d-ac1ff.firebasestorage.app"
  },
  "client": [
    {
      "client_info": {
        "mobilesdk_app_id": "1:230792036216:android:4d5092b33ffac7ace7928d",
        "android_client_info": {
          "package_name": "com.DefaultCompany.Final_Project_3D"
        }
      },
      "oauth_client": [],
      "api_key": [
        {
          "current_key": "AIzaSyAaLQ42sW4HuRNjvMqHcVkaqqOBlQnnnFQ"
        }
      ],
      "services": {
        "appinvite_service": {
          "other_platform_oauth_client": []
        }
      }
    }
  ],
  "configuration_version": "1"
}